sengpt/__init__.py
sengpt/__main__.py
sengpt/argparser.py
sengpt/config.py
sengpt/main.py
sengpt/re_gpt/__init__.py
sengpt/re_gpt/async_chatgpt.py
sengpt/re_gpt/errors.py
sengpt/re_gpt/sync_chatgpt.py
sengpt/re_gpt/utils.py
sengpt/utils.py
sengpt-0.1.2.dist-info/entry_points.txt
sengpt-0.1.2.dist-info/LICENSE
sengpt-0.1.2.dist-info/METADATA
sengpt-0.1.2.dist-info/WHEEL
sengpt-0.1.2.dist-info/RECORD
