Metadata-Version: 2.1
Name: sengpt
Version: 0.1.2
Summary: ChatGPT in your terminal, no OpenAI API key required
Home-page: https://github.com/SenZmaKi/Sengpt
License: GPL-3.0-only
Keywords: chatgpt,gpt,cli,command line,terminal,free gpt,free,no api key,no api,openai,openai chatgpt,chatgpt free
Author: SenZmaKi
Author-email: senzmaki@gmail.com
Requires-Python: >=3.11,<4.0
Classifier: License :: OSI Approved :: GNU General Public License v3 (GPLv3)
Classifier: Programming Language :: Python :: 3
Classifier: Programming Language :: Python :: 3.11
Classifier: Programming Language :: Python :: 3.12
Requires-Dist: appdirs (>=1.4.4,<2.0.0)
Requires-Dist: curl-cffi (>=0.5.10,<0.6.0)
Requires-Dist: pyperclip (>=1.8.2,<2.0.0)
Project-URL: Bug Tracker, https://github.com/SenZmaKi/Sengpt/issues
Project-URL: Repository, https://github.com/SenZmaKi/Sengpt
